[
  {
    "state_fips": "34",
    "district_id": "001",
    "district_name": "",
    "incumbent": {
      "name": "Mike Testa",
      "party": "R"
    },
    "members": [
      {
        "seat": 1,
        "seat_label": "",
        "incumbent": {
          "name": "Mike Testa",
          "party": "R"
        },
        "candidates": {
          "rep": "No candidate",
          "dem": "No candidate"
        }
      }
    ],
    "demographics": {
      "population": 164400,
      "rural_pct": 20.1,
      "town_pct": 7.7,
      "suburban_pct": 42.2,
      "urban_pct": 29.5,
      "income_brackets": {
        "lt_50k": 24.6,
        "between_50_100k": 28.8,
        "gt_150k": 32.4,
        "unknown_pct": 14.3
      },
      "college_pct": 18.7,
      "post_grad_pct": 8.7,
      "education_unknown_pct": 27.8,
      "white_pct": 63.2,
      "hispanic_pct": 15.9,
      "black_pct": 8.9,
      "asian_pct": 1.3,
      "other_pct": 10.8
    },
    "elections": [
      {
        "year": 2023,
        "dem_pct": 65.7,
        "rep_pct": 34.3,
        "winner": "D"
      }
    ],
    "view_margins": {
      "leg_2023": 31.3,
      "latest_leg": 31.3,
      "pres_2024": -10.9
    },
    "pres_2024_margin": -10.9,
    "gov_2022_margin": null,
    "top_ticket_totals": {
      "pres_2024": 102788,
      "gov_2022": 0
    },
    "candidates_2026": {
      "rep": "No candidate",
      "dem": "No candidate"
    }
  },
  {
    "state_fips": "34",
    "district_id": "002",
    "district_name": "",
    "incumbent": {
      "name": "Vincent J. Polistina",
      "party": "R"
    },
    "members": [
      {
        "seat": 1,
        "seat_label": "",
        "incumbent": {
          "name": "Vincent J. Polistina",
          "party": "R"
        },
        "candidates": {
          "rep": "No candidate",
          "dem": "No candidate"
        }
      }
    ],
    "demographics": {
      "population": 171765,
      "rural_pct": 9.7,
      "town_pct": 0.0,
      "suburban_pct": 76.5,
      "urban_pct": 13.4,
      "income_brackets": {
        "lt_50k": 22.2,
        "between_50_100k": 26.5,
        "gt_150k": 37.0,
        "unknown_pct": 14.3
      },
      "college_pct": 17.6,
      "post_grad_pct": 8.4,
      "education_unknown_pct": 28.7,
      "white_pct": 56.4,
      "hispanic_pct": 13.0,
      "black_pct": 12.9,
      "asian_pct": 7.6,
      "other_pct": 10.1
    },
    "elections": [
      {
        "year": 2023,
        "dem_pct": 44.8,
        "rep_pct": 52.2,
        "winner": "R"
      }
    ],
    "view_margins": {
      "leg_2023": -7.4,
      "latest_leg": -7.4,
      "pres_2024": 1.5
    },
    "pres_2024_margin": 1.5,
    "gov_2022_margin": null,
    "top_ticket_totals": {
      "pres_2024": 106890,
      "gov_2022": 0
    },
    "candidates_2026": {
      "rep": "No candidate",
      "dem": "No candidate"
    }
  },
  {
    "state_fips": "34",
    "district_id": "003",
    "district_name": "",
    "incumbent": {
      "name": "John Burzichelli",
      "party": "D"
    },
    "members": [
      {
        "seat": 1,
        "seat_label": "",
        "incumbent": {
          "name": "John Burzichelli",
          "party": "D"
        },
        "candidates": {
          "rep": "No candidate",
          "dem": "No candidate"
        }
      }
    ],
    "demographics": {
      "population": 178337,
      "rural_pct": 24.0,
      "town_pct": 7.2,
      "suburban_pct": 68.3,
      "urban_pct": 0.0,
      "income_brackets": {
        "lt_50k": 16.8,
        "between_50_100k": 27.7,
        "gt_150k": 42.9,
        "unknown_pct": 12.6
      },
      "college_pct": 18.5,
      "post_grad_pct": 8.9,
      "education_unknown_pct": 24.0,
      "white_pct": 72.6,
      "hispanic_pct": 5.7,
      "black_pct": 9.1,
      "asian_pct": 2.2,
      "other_pct": 10.4
    },
    "elections": [
      {
        "year": 2023,
        "dem_pct": 53.6,
        "rep_pct": 46.4,
        "winner": "D"
      }
    ],
    "view_margins": {
      "leg_2023": 7.2,
      "latest_leg": 7.2,
      "pres_2024": -7.5
    },
    "pres_2024_margin": -7.5,
    "gov_2022_margin": null,
    "top_ticket_totals": {
      "pres_2024": 122003,
      "gov_2022": 0
    },
    "candidates_2026": {
      "rep": "No candidate",
      "dem": "No candidate"
    }
  },
  {
    "state_fips": "34",
    "district_id": "004",
    "district_name": "",
    "incumbent": {
      "name": "Paul D. Moriarty",
      "party": "D"
    },
    "members": [
      {
        "seat": 1,
        "seat_label": "",
        "incumbent": {
          "name": "Paul D. Moriarty",
          "party": "D"
        },
        "candidates": {
          "rep": "No candidate",
          "dem": "No candidate"
        }
      }
    ],
    "demographics": {
      "population": 185053,
      "rural_pct": 11.9,
      "town_pct": 0.1,
      "suburban_pct": 87.6,
      "urban_pct": 0.0,
      "income_brackets": {
        "lt_50k": 15.0,
        "between_50_100k": 29.3,
        "gt_150k": 43.5,
        "unknown_pct": 12.3
      },
      "college_pct": 18.1,
      "post_grad_pct": 8.3,
      "education_unknown_pct": 24.1,
      "white_pct": 64.2,
      "hispanic_pct": 7.0,
      "black_pct": 16.2,
      "asian_pct": 3.0,
      "other_pct": 9.7
    },
    "elections": [
      {
        "year": 2023,
        "dem_pct": 53.5,
        "rep_pct": 43.5,
        "winner": "D"
      }
    ],
    "view_margins": {
      "leg_2023": 10.0,
      "latest_leg": 10.0,
      "pres_2024": 1.3
    },
    "pres_2024_margin": 1.3,
    "gov_2022_margin": null,
    "top_ticket_totals": {
      "pres_2024": 125064,
      "gov_2022": 0
    },
    "candidates_2026": {
      "rep": "No candidate",
      "dem": "No candidate"
    }
  },
  {
    "state_fips": "34",
    "district_id": "005",
    "district_name": "",
    "incumbent": {
      "name": "Nilsa Cruz-Perez",
      "party": "D"
    },
    "members": [
      {
        "seat": 1,
        "seat_label": "",
        "incumbent": {
          "name": "Nilsa Cruz-Perez",
          "party": "D"
        },
        "candidates": {
          "rep": "No candidate",
          "dem": "No candidate"
        }
      }
    ],
    "demographics": {
      "population": 166979,
      "rural_pct": 0.0,
      "town_pct": 0.0,
      "suburban_pct": 73.8,
      "urban_pct": 26.0,
      "income_brackets": {
        "lt_50k": 30.4,
        "between_50_100k": 26.3,
        "gt_150k": 27.1,
        "unknown_pct": 16.2
      },
      "college_pct": 16.0,
      "post_grad_pct": 6.0,
      "education_unknown_pct": 30.1,
      "white_pct": 48.3,
      "hispanic_pct": 19.8,
      "black_pct": 17.9,
      "asian_pct": 3.5,
      "other_pct": 10.5
    },
    "elections": [
      {
        "year": 2023,
        "dem_pct": 68.7,
        "rep_pct": 29.9,
        "winner": "D"
      }
    ],
    "view_margins": {
      "leg_2023": 38.7,
      "latest_leg": 38.7,
      "pres_2024": 29.1
    },
    "pres_2024_margin": 29.1,
    "gov_2022_margin": null,
    "top_ticket_totals": {
      "pres_2024": 94267,
      "gov_2022": 0
    },
    "candidates_2026": {
      "rep": "No candidate",
      "dem": "No candidate"
    }
  },
  {
    "state_fips": "34",
    "district_id": "006",
    "district_name": "",
    "incumbent": {
      "name": "James Beach",
      "party": "D"
    },
    "members": [
      {
        "seat": 1,
        "seat_label": "",
        "incumbent": {
          "name": "James Beach",
          "party": "D"
        },
        "candidates": {
          "rep": "No candidate",
          "dem": "No candidate"
        }
      }
    ],
    "demographics": {
      "population": 179284,
      "rural_pct": 0.1,
      "town_pct": 0.0,
      "suburban_pct": 99.6,
      "urban_pct": 0.0,
      "income_brackets": {
        "lt_50k": 14.6,
        "between_50_100k": 24.3,
        "gt_150k": 48.6,
        "unknown_pct": 12.4
      },
      "college_pct": 17.9,
      "post_grad_pct": 11.2,
      "education_unknown_pct": 24.8,
      "white_pct": 65.9,
      "hispanic_pct": 7.0,
      "black_pct": 9.9,
      "asian_pct": 7.1,
      "other_pct": 10.1
    },
    "elections": [
      {
        "year": 2023,
        "dem_pct": 70.0,
        "rep_pct": 30.0,
        "winner": "D"
      }
    ],
    "view_margins": {
      "leg_2023": 40.0,
      "latest_leg": 40.0,
      "pres_2024": 27.6
    },
    "pres_2024_margin": 27.6,
    "gov_2022_margin": null,
    "top_ticket_totals": {
      "pres_2024": 115648,
      "gov_2022": 0
    },
    "candidates_2026": {
      "rep": "No candidate",
      "dem": "No candidate"
    }
  },
  {
    "state_fips": "34",
    "district_id": "007",
    "district_name": "",
    "incumbent": {
      "name": "Troy Singleton",
      "party": "D"
    },
    "members": [
      {
        "seat": 1,
        "seat_label": "",
        "incumbent": {
          "name": "Troy Singleton",
          "party": "D"
        },
        "candidates": {
          "rep": "No candidate",
          "dem": "No candidate"
        }
      }
    ],
    "demographics": {
      "population": 187843,
      "rural_pct": 0.6,
      "town_pct": 0.1,
      "suburban_pct": 98.9,
      "urban_pct": 0.0,
      "income_brackets": {
        "lt_50k": 13.4,
        "between_50_100k": 27.7,
        "gt_150k": 46.8,
        "unknown_pct": 12.2
      },
      "college_pct": 18.7,
      "post_grad_pct": 10.1,
      "education_unknown_pct": 24.4,
      "white_pct": 56.4,
      "hispanic_pct": 6.6,
      "black_pct": 21.5,
      "asian_pct": 6.0,
      "other_pct": 9.4
    },
    "elections": [
      {
        "year": 2023,
        "dem_pct": 67.7,
        "rep_pct": 32.3,
        "winner": "D"
      }
    ],
    "view_margins": {
      "leg_2023": 35.5,
      "latest_leg": 35.5,
      "pres_2024": 28.8
    },
    "pres_2024_margin": 28.8,
    "gov_2022_margin": null,
    "top_ticket_totals": {
      "pres_2024": 112682,
      "gov_2022": 0
    },
    "candidates_2026": {
      "rep": "No candidate",
      "dem": "No candidate"
    }
  },
  {
    "state_fips": "34",
    "district_id": "008",
    "district_name": "",
    "incumbent": {
      "name": "Latham Tiver",
      "party": "R"
    },
    "members": [
      {
        "seat": 1,
        "seat_label": "",
        "incumbent": {
          "name": "Latham Tiver",
          "party": "R"
        },
        "candidates": {
          "rep": "No candidate",
          "dem": "No candidate"
        }
      }
    ],
    "demographics": {
      "population": 185318,
      "rural_pct": 17.6,
      "town_pct": 13.1,
      "suburban_pct": 68.8,
      "urban_pct": 0.0,
      "income_brackets": {
        "lt_50k": 12.1,
        "between_50_100k": 24.3,
        "gt_150k": 52.4,
        "unknown_pct": 11.2
      },
      "college_pct": 19.8,
      "post_grad_pct": 10.3,
      "education_unknown_pct": 22.7,
      "white_pct": 71.3,
      "hispanic_pct": 6.9,
      "black_pct": 8.1,
      "asian_pct": 4.3,
      "other_pct": 9.4
    },
    "elections": [
      {
        "year": 2023,
        "dem_pct": 49.0,
        "rep_pct": 51.0,
        "winner": "R"
      }
    ],
    "view_margins": {
      "leg_2023": -2.1,
      "latest_leg": -2.1,
      "pres_2024": 1.0
    },
    "pres_2024_margin": 1.0,
    "gov_2022_margin": null,
    "top_ticket_totals": {
      "pres_2024": 116218,
      "gov_2022": 0
    },
    "candidates_2026": {
      "rep": "No candidate",
      "dem": "No candidate"
    }
  },
  {
    "state_fips": "34",
    "district_id": "009",
    "district_name": "",
    "incumbent": {
      "name": "Carmen Amato",
      "party": "R"
    },
    "members": [
      {
        "seat": 1,
        "seat_label": "",
        "incumbent": {
          "name": "Carmen Amato",
          "party": "R"
        },
        "candidates": {
          "rep": "No candidate",
          "dem": "No candidate"
        }
      }
    ],
    "demographics": {
      "population": 203360,
      "rural_pct": 6.6,
      "town_pct": 9.0,
      "suburban_pct": 83.8,
      "urban_pct": 0.0,
      "income_brackets": {
        "lt_50k": 15.6,
        "between_50_100k": 30.5,
        "gt_150k": 43.6,
        "unknown_pct": 10.2
      },
      "college_pct": 21.2,
      "post_grad_pct": 11.0,
      "education_unknown_pct": 21.7,
      "white_pct": 81.1,
      "hispanic_pct": 6.8,
      "black_pct": 1.5,
      "asian_pct": 1.6,
      "other_pct": 9.1
    },
    "elections": [
      {
        "year": 2023,
        "dem_pct": 32.1,
        "rep_pct": 67.9,
        "winner": "R"
      }
    ],
    "view_margins": {
      "leg_2023": -35.9,
      "latest_leg": -35.9,
      "pres_2024": -29.4
    },
    "pres_2024_margin": -29.4,
    "gov_2022_margin": null,
    "top_ticket_totals": {
      "pres_2024": 145395,
      "gov_2022": 0
    },
    "candidates_2026": {
      "rep": "No candidate",
      "dem": "No candidate"
    }
  },
  {
    "state_fips": "34",
    "district_id": "010",
    "district_name": "",
    "incumbent": {
      "name": "James W. Holzapfel",
      "party": "R"
    },
    "members": [
      {
        "seat": 1,
        "seat_label": "",
        "incumbent": {
          "name": "James W. Holzapfel",
          "party": "R"
        },
        "candidates": {
          "rep": "No candidate",
          "dem": "No candidate"
        }
      }
    ],
    "demographics": {
      "population": 182534,
      "rural_pct": 0.2,
      "town_pct": 0.0,
      "suburban_pct": 99.1,
      "urban_pct": 0.0,
      "income_brackets": {
        "lt_50k": 10.5,
        "between_50_100k": 24.1,
        "gt_150k": 54.8,
        "unknown_pct": 10.7
      },
      "college_pct": 20.3,
      "post_grad_pct": 11.5,
      "education_unknown_pct": 22.6,
      "white_pct": 79.3,
      "hispanic_pct": 7.6,
      "black_pct": 1.6,
      "asian_pct": 2.1,
      "other_pct": 9.3
    },
    "elections": [
      {
        "year": 2023,
        "dem_pct": 33.4,
        "rep_pct": 66.6,
        "winner": "R"
      }
    ],
    "view_margins": {
      "leg_2023": -33.1,
      "latest_leg": -33.1,
      "pres_2024": -27.8
    },
    "pres_2024_margin": -27.8,
    "gov_2022_margin": null,
    "top_ticket_totals": {
      "pres_2024": 129821,
      "gov_2022": 0
    },
    "candidates_2026": {
      "rep": "No candidate",
      "dem": "No candidate"
    }
  },
  {
    "state_fips": "34",
    "district_id": "011",
    "district_name": "",
    "incumbent": {
      "name": "Vin Gopal",
      "party": "D"
    },
    "members": [
      {
        "seat": 1,
        "seat_label": "",
        "incumbent": {
          "name": "Vin Gopal",
          "party": "D"
        },
        "candidates": {
          "rep": "No candidate",
          "dem": "No candidate"
        }
      }
    ],
    "demographics": {
      "population": 165201,
      "rural_pct": 2.6,
      "town_pct": 0.0,
      "suburban_pct": 97.0,
      "urban_pct": 0.0,
      "income_brackets": {
        "lt_50k": 12.5,
        "between_50_100k": 19.3,
        "gt_150k": 55.4,
        "unknown_pct": 12.8
      },
      "college_pct": 19.3,
      "post_grad_pct": 12.0,
      "education_unknown_pct": 25.4,
      "white_pct": 65.1,
      "hispanic_pct": 10.5,
      "black_pct": 10.3,
      "asian_pct": 4.1,
      "other_pct": 10.0
    },
    "elections": [
      {
        "year": 2023,
        "dem_pct": 60.3,
        "rep_pct": 38.9,
        "winner": "D"
      }
    ],
    "view_margins": {
      "leg_2023": 21.4,
      "latest_leg": 21.4,
      "pres_2024": 4.2
    },
    "pres_2024_margin": 4.2,
    "gov_2022_margin": null,
    "top_ticket_totals": {
      "pres_2024": 113394,
      "gov_2022": 0
    },
    "candidates_2026": {
      "rep": "No candidate",
      "dem": "No candidate"
    }
  },
  {
    "state_fips": "34",
    "district_id": "012",
    "district_name": "",
    "incumbent": {
      "name": "Owen Henry",
      "party": "R"
    },
    "members": [
      {
        "seat": 1,
        "seat_label": "",
        "incumbent": {
          "name": "Owen Henry",
          "party": "R"
        },
        "candidates": {
          "rep": "No candidate",
          "dem": "No candidate"
        }
      }
    ],
    "demographics": {
      "population": 173966,
      "rural_pct": 15.9,
      "town_pct": 4.1,
      "suburban_pct": 79.5,
      "urban_pct": 0.0,
      "income_brackets": {
        "lt_50k": 9.2,
        "between_50_100k": 19.9,
        "gt_150k": 59.2,
        "unknown_pct": 11.8
      },
      "college_pct": 18.9,
      "post_grad_pct": 10.0,
      "education_unknown_pct": 24.7,
      "white_pct": 70.0,
      "hispanic_pct": 9.3,
      "black_pct": 2.8,
      "asian_pct": 7.4,
      "other_pct": 10.5
    },
    "elections": [
      {
        "year": 2023,
        "dem_pct": 36.1,
        "rep_pct": 62.2,
        "winner": "R"
      }
    ],
    "view_margins": {
      "leg_2023": -26.1,
      "latest_leg": -26.1,
      "pres_2024": -25.3
    },
    "pres_2024_margin": -25.3,
    "gov_2022_margin": null,
    "top_ticket_totals": {
      "pres_2024": 119932,
      "gov_2022": 0
    },
    "candidates_2026": {
      "rep": "No candidate",
      "dem": "No candidate"
    }
  },
  {
    "state_fips": "34",
    "district_id": "013",
    "district_name": "",
    "incumbent": {
      "name": "Declan O'Scanlon",
      "party": "R"
    },
    "members": [
      {
        "seat": 1,
        "seat_label": "",
        "incumbent": {
          "name": "Declan O'Scanlon",
          "party": "R"
        },
        "candidates": {
          "rep": "No candidate",
          "dem": "No candidate"
        }
      }
    ],
    "demographics": {
      "population": 188995,
      "rural_pct": 0.1,
      "town_pct": 0.0,
      "suburban_pct": 99.5,
      "urban_pct": 0.0,
      "income_brackets": {
        "lt_50k": 6.9,
        "between_50_100k": 16.7,
        "gt_150k": 65.8,
        "unknown_pct": 10.5
      },
      "college_pct": 20.1,
      "post_grad_pct": 12.4,
      "education_unknown_pct": 22.3,
      "white_pct": 74.5,
      "hispanic_pct": 7.0,
      "black_pct": 1.6,
      "asian_pct": 7.3,
      "other_pct": 9.6
    },
    "elections": [
      {
        "year": 2023,
        "dem_pct": 41.2,
        "rep_pct": 58.8,
        "winner": "R"
      }
    ],
    "view_margins": {
      "leg_2023": -17.6,
      "latest_leg": -17.6,
      "pres_2024": -15.5
    },
    "pres_2024_margin": -15.5,
    "gov_2022_margin": null,
    "top_ticket_totals": {
      "pres_2024": 134640,
      "gov_2022": 0
    },
    "candidates_2026": {
      "rep": "No candidate",
      "dem": "No candidate"
    }
  },
  {
    "state_fips": "34",
    "district_id": "014",
    "district_name": "",
    "incumbent": {
      "name": "Linda R. Greenstein",
      "party": "D"
    },
    "members": [
      {
        "seat": 1,
        "seat_label": "",
        "incumbent": {
          "name": "Linda R. Greenstein",
          "party": "D"
        },
        "candidates": {
          "rep": "No candidate",
          "dem": "No candidate"
        }
      }
    ],
    "demographics": {
      "population": 172786,
      "rural_pct": 5.5,
      "town_pct": 0.0,
      "suburban_pct": 94.0,
      "urban_pct": 0.1,
      "income_brackets": {
        "lt_50k": 10.4,
        "between_50_100k": 23.3,
        "gt_150k": 54.4,
        "unknown_pct": 12.0
      },
      "college_pct": 19.3,
      "post_grad_pct": 12.6,
      "education_unknown_pct": 25.9,
      "white_pct": 57.9,
      "hispanic_pct": 10.9,
      "black_pct": 5.5,
      "asian_pct": 15.5,
      "other_pct": 10.2
    },
    "elections": [
      {
        "year": 2023,
        "dem_pct": 59.8,
        "rep_pct": 40.2,
        "winner": "D"
      }
    ],
    "view_margins": {
      "leg_2023": 19.5,
      "latest_leg": 19.5,
      "pres_2024": 10.9
    },
    "pres_2024_margin": 10.9,
    "gov_2022_margin": null,
    "top_ticket_totals": {
      "pres_2024": 111652,
      "gov_2022": 0
    },
    "candidates_2026": {
      "rep": "No candidate",
      "dem": "No candidate"
    }
  },
  {
    "state_fips": "34",
    "district_id": "015",
    "district_name": "",
    "incumbent": {
      "name": "Shirley Turner",
      "party": "D"
    },
    "members": [
      {
        "seat": 1,
        "seat_label": "",
        "incumbent": {
          "name": "Shirley Turner",
          "party": "D"
        },
        "candidates": {
          "rep": "No candidate",
          "dem": "No candidate"
        }
      }
    ],
    "demographics": {
      "population": 158541,
      "rural_pct": 13.3,
      "town_pct": 0.7,
      "suburban_pct": 58.7,
      "urban_pct": 27.1,
      "income_brackets": {
        "lt_50k": 19.8,
        "between_50_100k": 18.7,
        "gt_150k": 47.0,
        "unknown_pct": 14.6
      },
      "college_pct": 16.7,
      "post_grad_pct": 12.0,
      "education_unknown_pct": 28.9,
      "white_pct": 46.6,
      "hispanic_pct": 11.2,
      "black_pct": 21.5,
      "asian_pct": 10.4,
      "other_pct": 10.2
    },
    "elections": [
      {
        "year": 2023,
        "dem_pct": 73.2,
        "rep_pct": 26.8,
        "winner": "D"
      }
    ],
    "view_margins": {
      "leg_2023": 46.4,
      "latest_leg": 46.4,
      "pres_2024": 41.3
    },
    "pres_2024_margin": 41.3,
    "gov_2022_margin": null,
    "top_ticket_totals": {
      "pres_2024": 88612,
      "gov_2022": 0
    },
    "candidates_2026": {
      "rep": "No candidate",
      "dem": "No candidate"
    }
  },
  {
    "state_fips": "34",
    "district_id": "016",
    "district_name": "",
    "incumbent": {
      "name": "Andrew Zwicker",
      "party": "D"
    },
    "members": [
      {
        "seat": 1,
        "seat_label": "",
        "incumbent": {
          "name": "Andrew Zwicker",
          "party": "D"
        },
        "candidates": {
          "rep": "No candidate",
          "dem": "No candidate"
        }
      }
    ],
    "demographics": {
      "population": 178091,
      "rural_pct": 13.4,
      "town_pct": 0.0,
      "suburban_pct": 74.6,
      "urban_pct": 11.7,
      "income_brackets": {
        "lt_50k": 5.5,
        "between_50_100k": 13.8,
        "gt_150k": 68.9,
        "unknown_pct": 11.8
      },
      "college_pct": 18.6,
      "post_grad_pct": 15.3,
      "education_unknown_pct": 25.5,
      "white_pct": 60.6,
      "hispanic_pct": 6.6,
      "black_pct": 2.5,
      "asian_pct": 19.7,
      "other_pct": 10.7
    },
    "elections": [
      {
        "year": 2023,
        "dem_pct": 56.5,
        "rep_pct": 42.0,
        "winner": "D"
      }
    ],
    "view_margins": {
      "leg_2023": 14.4,
      "latest_leg": 14.4,
      "pres_2024": 12.0
    },
    "pres_2024_margin": 12.0,
    "gov_2022_margin": null,
    "top_ticket_totals": {
      "pres_2024": 111403,
      "gov_2022": 0
    },
    "candidates_2026": {
      "rep": "No candidate",
      "dem": "No candidate"
    }
  },
  {
    "state_fips": "34",
    "district_id": "017",
    "district_name": "",
    "incumbent": {
      "name": "Bob Smith",
      "party": "D"
    },
    "members": [
      {
        "seat": 1,
        "seat_label": "",
        "incumbent": {
          "name": "Bob Smith",
          "party": "D"
        },
        "candidates": {
          "rep": "No candidate",
          "dem": "No candidate"
        }
      }
    ],
    "demographics": {
      "population": 143961,
      "rural_pct": 1.3,
      "town_pct": 0.0,
      "suburban_pct": 83.4,
      "urban_pct": 15.0,
      "income_brackets": {
        "lt_50k": 13.6,
        "between_50_100k": 21.2,
        "gt_150k": 47.4,
        "unknown_pct": 17.9
      },
      "college_pct": 16.0,
      "post_grad_pct": 9.5,
      "education_unknown_pct": 33.8,
      "white_pct": 33.9,
      "hispanic_pct": 17.4,
      "black_pct": 16.6,
      "asian_pct": 19.5,
      "other_pct": 12.7
    },
    "elections": [
      {
        "year": 2023,
        "dem_pct": 72.8,
        "rep_pct": 27.2,
        "winner": "D"
      }
    ],
    "view_margins": {
      "leg_2023": 45.6,
      "latest_leg": 45.6,
      "pres_2024": 32.1
    },
    "pres_2024_margin": 32.1,
    "gov_2022_margin": null,
    "top_ticket_totals": {
      "pres_2024": 82128,
      "gov_2022": 0
    },
    "candidates_2026": {
      "rep": "No candidate",
      "dem": "No candidate"
    }
  },
  {
    "state_fips": "34",
    "district_id": "018",
    "district_name": "",
    "incumbent": {
      "name": "Patrick J. Diegnan",
      "party": "D"
    },
    "members": [
      {
        "seat": 1,
        "seat_label": "",
        "incumbent": {
          "name": "Patrick J. Diegnan",
          "party": "D"
        },
        "candidates": {
          "rep": "No candidate",
          "dem": "No candidate"
        }
      }
    ],
    "demographics": {
      "population": 161546,
      "rural_pct": 0.3,
      "town_pct": 0.0,
      "suburban_pct": 99.4,
      "urban_pct": 0.0,
      "income_brackets": {
        "lt_50k": 8.8,
        "between_50_100k": 19.0,
        "gt_150k": 58.8,
        "unknown_pct": 13.4
      },
      "college_pct": 16.9,
      "post_grad_pct": 11.7,
      "education_unknown_pct": 29.6,
      "white_pct": 47.1,
      "hispanic_pct": 11.7,
      "black_pct": 4.5,
      "asian_pct": 25.6,
      "other_pct": 11.1
    },
    "elections": [
      {
        "year": 2023,
        "dem_pct": 64.0,
        "rep_pct": 36.0,
        "winner": "D"
      }
    ],
    "view_margins": {
      "leg_2023": 28.0,
      "latest_leg": 28.0,
      "pres_2024": 10.2
    },
    "pres_2024_margin": 10.2,
    "gov_2022_margin": null,
    "top_ticket_totals": {
      "pres_2024": 98009,
      "gov_2022": 0
    },
    "candidates_2026": {
      "rep": "No candidate",
      "dem": "No candidate"
    }
  },
  {
    "state_fips": "34",
    "district_id": "019",
    "district_name": "",
    "incumbent": {
      "name": "Joe F. Vitale",
      "party": "D"
    },
    "members": [
      {
        "seat": 1,
        "seat_label": "",
        "incumbent": {
          "name": "Joe F. Vitale",
          "party": "D"
        },
        "candidates": {
          "rep": "No candidate",
          "dem": "No candidate"
        }
      }
    ],
    "demographics": {
      "population": 157641,
      "rural_pct": 0.1,
      "town_pct": 0.0,
      "suburban_pct": 99.6,
      "urban_pct": 0.0,
      "income_brackets": {
        "lt_50k": 17.6,
        "between_50_100k": 25.5,
        "gt_150k": 40.5,
        "unknown_pct": 16.3
      },
      "college_pct": 15.4,
      "post_grad_pct": 6.3,
      "education_unknown_pct": 34.1,
      "white_pct": 37.0,
      "hispanic_pct": 31.2,
      "black_pct": 7.3,
      "asian_pct": 13.2,
      "other_pct": 11.3
    },
    "elections": [
      {
        "year": 2023,
        "dem_pct": 63.2,
        "rep_pct": 36.8,
        "winner": "D"
      }
    ],
    "view_margins": {
      "leg_2023": 26.4,
      "latest_leg": 26.4,
      "pres_2024": 1.1
    },
    "pres_2024_margin": 1.1,
    "gov_2022_margin": null,
    "top_ticket_totals": {
      "pres_2024": 87729,
      "gov_2022": 0
    },
    "candidates_2026": {
      "rep": "No candidate",
      "dem": "No candidate"
    }
  },
  {
    "state_fips": "34",
    "district_id": "020",
    "district_name": "",
    "incumbent": {
      "name": "Joseph Cryan",
      "party": "D"
    },
    "members": [
      {
        "seat": 1,
        "seat_label": "",
        "incumbent": {
          "name": "Joseph Cryan",
          "party": "D"
        },
        "candidates": {
          "rep": "No candidate",
          "dem": "No candidate"
        }
      }
    ],
    "demographics": {
      "population": 136629,
      "rural_pct": 0.0,
      "town_pct": 0.0,
      "suburban_pct": 99.7,
      "urban_pct": 0.0,
      "income_brackets": {
        "lt_50k": 27.4,
        "between_50_100k": 24.1,
        "gt_150k": 28.9,
        "unknown_pct": 19.6
      },
      "college_pct": 14.3,
      "post_grad_pct": 5.4,
      "education_unknown_pct": 38.5,
      "white_pct": 21.0,
      "hispanic_pct": 40.9,
      "black_pct": 22.9,
      "asian_pct": 3.8,
      "other_pct": 11.3
    },
    "elections": [
      {
        "year": 2023,
        "dem_pct": 74.7,
        "rep_pct": 25.3,
        "winner": "D"
      }
    ],
    "view_margins": {
      "leg_2023": 49.4,
      "latest_leg": 49.4,
      "pres_2024": 24.2
    },
    "pres_2024_margin": 24.2,
    "gov_2022_margin": null,
    "top_ticket_totals": {
      "pres_2024": 72769,
      "gov_2022": 0
    },
    "candidates_2026": {
      "rep": "No candidate",
      "dem": "No candidate"
    }
  },
  {
    "state_fips": "34",
    "district_id": "021",
    "district_name": "",
    "incumbent": {
      "name": "Jon Bramnick",
      "party": "R"
    },
    "members": [
      {
        "seat": 1,
        "seat_label": "",
        "incumbent": {
          "name": "Jon Bramnick",
          "party": "R"
        },
        "candidates": {
          "rep": "No candidate",
          "dem": "No candidate"
        }
      }
    ],
    "demographics": {
      "population": 186536,
      "rural_pct": 3.7,
      "town_pct": 0.0,
      "suburban_pct": 96.0,
      "urban_pct": 0.0,
      "income_brackets": {
        "lt_50k": 5.0,
        "between_50_100k": 11.4,
        "gt_150k": 72.8,
        "unknown_pct": 10.9
      },
      "college_pct": 19.8,
      "post_grad_pct": 15.6,
      "education_unknown_pct": 23.9,
      "white_pct": 68.0,
      "hispanic_pct": 9.1,
      "black_pct": 2.1,
      "asian_pct": 10.9,
      "other_pct": 10.0
    },
    "elections": [
      {
        "year": 2023,
        "dem_pct": 46.5,
        "rep_pct": 53.5,
        "winner": "R"
      }
    ],
    "view_margins": {
      "leg_2023": -7.0,
      "latest_leg": -7.0,
      "pres_2024": 12.0
    },
    "pres_2024_margin": 12.0,
    "gov_2022_margin": null,
    "top_ticket_totals": {
      "pres_2024": 130967,
      "gov_2022": 0
    },
    "candidates_2026": {
      "rep": "No candidate",
      "dem": "No candidate"
    }
  },
  {
    "state_fips": "34",
    "district_id": "022",
    "district_name": "",
    "incumbent": {
      "name": "Nicholas Scutari",
      "party": "D"
    },
    "members": [
      {
        "seat": 1,
        "seat_label": "",
        "incumbent": {
          "name": "Nicholas Scutari",
          "party": "D"
        },
        "candidates": {
          "rep": "No candidate",
          "dem": "No candidate"
        }
      }
    ],
    "demographics": {
      "population": 163143,
      "rural_pct": 0.0,
      "town_pct": 0.0,
      "suburban_pct": 99.6,
      "urban_pct": 0.0,
      "income_brackets": {
        "lt_50k": 16.2,
        "between_50_100k": 24.2,
        "gt_150k": 45.2,
        "unknown_pct": 14.5
      },
      "college_pct": 17.6,
      "post_grad_pct": 8.6,
      "education_unknown_pct": 29.4,
      "white_pct": 42.1,
      "hispanic_pct": 22.7,
      "black_pct": 20.7,
      "asian_pct": 4.2,
      "other_pct": 10.2
    },
    "elections": [
      {
        "year": 2023,
        "dem_pct": 66.2,
        "rep_pct": 33.8,
        "winner": "D"
      }
    ],
    "view_margins": {
      "leg_2023": 32.4,
      "latest_leg": 32.4,
      "pres_2024": 24.8
    },
    "pres_2024_margin": 24.8,
    "gov_2022_margin": null,
    "top_ticket_totals": {
      "pres_2024": 103474,
      "gov_2022": 0
    },
    "candidates_2026": {
      "rep": "No candidate",
      "dem": "No candidate"
    }
  },
  {
    "state_fips": "34",
    "district_id": "023",
    "district_name": "",
    "incumbent": {
      "name": "Doug Steinhardt",
      "party": "R"
    },
    "members": [
      {
        "seat": 1,
        "seat_label": "",
        "incumbent": {
          "name": "Doug Steinhardt",
          "party": "R"
        },
        "candidates": {
          "rep": "No candidate",
          "dem": "No candidate"
        }
      }
    ],
    "demographics": {
      "population": 186548,
      "rural_pct": 34.2,
      "town_pct": 8.8,
      "suburban_pct": 56.7,
      "urban_pct": 0.0,
      "income_brackets": {
        "lt_50k": 10.8,
        "between_50_100k": 22.0,
        "gt_150k": 55.2,
        "unknown_pct": 12.1
      },
      "college_pct": 19.5,
      "post_grad_pct": 11.2,
      "education_unknown_pct": 24.9,
      "white_pct": 69.8,
      "hispanic_pct": 10.4,
      "black_pct": 2.7,
      "asian_pct": 6.7,
      "other_pct": 10.4
    },
    "elections": [
      {
        "year": 2023,
        "dem_pct": 42.3,
        "rep_pct": 57.7,
        "winner": "R"
      }
    ],
    "view_margins": {
      "leg_2023": -15.4,
      "latest_leg": -15.4,
      "pres_2024": -11.8
    },
    "pres_2024_margin": -11.8,
    "gov_2022_margin": null,
    "top_ticket_totals": {
      "pres_2024": 123034,
      "gov_2022": 0
    },
    "candidates_2026": {
      "rep": "No candidate",
      "dem": "No candidate"
    }
  },
  {
    "state_fips": "34",
    "district_id": "024",
    "district_name": "",
    "incumbent": {
      "name": "Parker Space",
      "party": "R"
    },
    "members": [
      {
        "seat": 1,
        "seat_label": "",
        "incumbent": {
          "name": "Parker Space",
          "party": "R"
        },
        "candidates": {
          "rep": "No candidate",
          "dem": "No candidate"
        }
      }
    ],
    "demographics": {
      "population": 197169,
      "rural_pct": 33.8,
      "town_pct": 21.0,
      "suburban_pct": 44.8,
      "urban_pct": 0.0,
      "income_brackets": {
        "lt_50k": 8.7,
        "between_50_100k": 22.1,
        "gt_150k": 58.3,
        "unknown_pct": 11.0
      },
      "college_pct": 19.9,
      "post_grad_pct": 10.8,
      "education_unknown_pct": 23.1,
      "white_pct": 75.6,
      "hispanic_pct": 9.6,
      "black_pct": 1.6,
      "asian_pct": 3.4,
      "other_pct": 9.8
    },
    "elections": [
      {
        "year": 2023,
        "dem_pct": 35.9,
        "rep_pct": 64.1,
        "winner": "R"
      }
    ],
    "view_margins": {
      "leg_2023": -28.2,
      "latest_leg": -28.2,
      "pres_2024": -19.6
    },
    "pres_2024_margin": -19.6,
    "gov_2022_margin": null,
    "top_ticket_totals": {
      "pres_2024": 140775,
      "gov_2022": 0
    },
    "candidates_2026": {
      "rep": "No candidate",
      "dem": "No candidate"
    }
  },
  {
    "state_fips": "34",
    "district_id": "025",
    "district_name": "",
    "incumbent": {
      "name": "Anthony M. Bucco",
      "party": "R"
    },
    "members": [
      {
        "seat": 1,
        "seat_label": "",
        "incumbent": {
          "name": "Anthony M. Bucco",
          "party": "R"
        },
        "candidates": {
          "rep": "No candidate",
          "dem": "No candidate"
        }
      }
    ],
    "demographics": {
      "population": 182206,
      "rural_pct": 12.2,
      "town_pct": 6.5,
      "suburban_pct": 81.0,
      "urban_pct": 0.0,
      "income_brackets": {
        "lt_50k": 7.0,
        "between_50_100k": 17.5,
        "gt_150k": 63.7,
        "unknown_pct": 11.7
      },
      "college_pct": 19.7,
      "post_grad_pct": 12.5,
      "education_unknown_pct": 24.9,
      "white_pct": 69.1,
      "hispanic_pct": 13.7,
      "black_pct": 1.9,
      "asian_pct": 5.3,
      "other_pct": 10.0
    },
    "elections": [
      {
        "year": 2023,
        "dem_pct": 47.3,
        "rep_pct": 52.7,
        "winner": "R"
      }
    ],
    "view_margins": {
      "leg_2023": -5.3,
      "latest_leg": -5.3,
      "pres_2024": -0.7
    },
    "pres_2024_margin": -0.7,
    "gov_2022_margin": null,
    "top_ticket_totals": {
      "pres_2024": 129122,
      "gov_2022": 0
    },
    "candidates_2026": {
      "rep": "No candidate",
      "dem": "No candidate"
    }
  },
  {
    "state_fips": "34",
    "district_id": "026",
    "district_name": "",
    "incumbent": {
      "name": "Joseph Pennacchio",
      "party": "R"
    },
    "members": [
      {
        "seat": 1,
        "seat_label": "",
        "incumbent": {
          "name": "Joseph Pennacchio",
          "party": "R"
        },
        "candidates": {
          "rep": "No candidate",
          "dem": "No candidate"
        }
      }
    ],
    "demographics": {
      "population": 175670,
      "rural_pct": 2.4,
      "town_pct": 0.0,
      "suburban_pct": 97.1,
      "urban_pct": 0.0,
      "income_brackets": {
        "lt_50k": 6.3,
        "between_50_100k": 17.3,
        "gt_150k": 65.4,
        "unknown_pct": 10.9
      },
      "college_pct": 20.6,
      "post_grad_pct": 13.1,
      "education_unknown_pct": 24.2,
      "white_pct": 67.0,
      "hispanic_pct": 9.2,
      "black_pct": 1.5,
      "asian_pct": 12.5,
      "other_pct": 9.8
    },
    "elections": [
      {
        "year": 2023,
        "dem_pct": 43.2,
        "rep_pct": 56.8,
        "winner": "R"
      }
    ],
    "view_margins": {
      "leg_2023": -13.5,
      "latest_leg": -13.5,
      "pres_2024": -9.0
    },
    "pres_2024_margin": -9.0,
    "gov_2022_margin": null,
    "top_ticket_totals": {
      "pres_2024": 128090,
      "gov_2022": 0
    },
    "candidates_2026": {
      "rep": "No candidate",
      "dem": "No candidate"
    }
  },
  {
    "state_fips": "34",
    "district_id": "027",
    "district_name": "",
    "incumbent": {
      "name": "John F. McKeon",
      "party": "D"
    },
    "members": [
      {
        "seat": 1,
        "seat_label": "",
        "incumbent": {
          "name": "John F. McKeon",
          "party": "D"
        },
        "candidates": {
          "rep": "No candidate",
          "dem": "No candidate"
        }
      }
    ],
    "demographics": {
      "population": 183718,
      "rural_pct": 0.0,
      "town_pct": 0.0,
      "suburban_pct": 99.7,
      "urban_pct": 0.0,
      "income_brackets": {
        "lt_50k": 9.5,
        "between_50_100k": 17.7,
        "gt_150k": 59.7,
        "unknown_pct": 13.0
      },
      "college_pct": 18.1,
      "post_grad_pct": 12.7,
      "education_unknown_pct": 28.5,
      "white_pct": 49.0,
      "hispanic_pct": 17.9,
      "black_pct": 11.2,
      "asian_pct": 11.5,
      "other_pct": 10.4
    },
    "elections": [
      {
        "year": 2023,
        "dem_pct": 71.1,
        "rep_pct": 28.9,
        "winner": "D"
      }
    ],
    "view_margins": {
      "leg_2023": 42.3,
      "latest_leg": 42.3,
      "pres_2024": 31.1
    },
    "pres_2024_margin": 31.1,
    "gov_2022_margin": null,
    "top_ticket_totals": {
      "pres_2024": 113531,
      "gov_2022": 0
    },
    "candidates_2026": {
      "rep": "No candidate",
      "dem": "No candidate"
    }
  },
  {
    "state_fips": "34",
    "district_id": "028",
    "district_name": "",
    "incumbent": {
      "name": "Renee Burgess",
      "party": "D"
    },
    "members": [
      {
        "seat": 1,
        "seat_label": "",
        "incumbent": {
          "name": "Renee Burgess",
          "party": "D"
        },
        "candidates": {
          "rep": "No candidate",
          "dem": "No candidate"
        }
      }
    ],
    "demographics": {
      "population": 145471,
      "rural_pct": 0.0,
      "town_pct": 0.0,
      "suburban_pct": 58.6,
      "urban_pct": 41.2,
      "income_brackets": {
        "lt_50k": 32.9,
        "between_50_100k": 21.8,
        "gt_150k": 25.2,
        "unknown_pct": 20.1
      },
      "college_pct": 13.2,
      "post_grad_pct": 6.0,
      "education_unknown_pct": 37.5,
      "white_pct": 16.9,
      "hispanic_pct": 9.1,
      "black_pct": 60.6,
      "asian_pct": 2.4,
      "other_pct": 11.1
    },
    "elections": [
      {
        "year": 2023,
        "dem_pct": 100.0,
        "rep_pct": 0.0,
        "winner": "D"
      }
    ],
    "view_margins": {
      "leg_2023": 100.0,
      "latest_leg": 100.0,
      "pres_2024": 76.7
    },
    "pres_2024_margin": 76.7,
    "gov_2022_margin": null,
    "top_ticket_totals": {
      "pres_2024": 73677,
      "gov_2022": 0
    },
    "candidates_2026": {
      "rep": "No candidate",
      "dem": "No candidate"
    }
  },
  {
    "state_fips": "34",
    "district_id": "029",
    "district_name": "",
    "incumbent": {
      "name": "Teresa Ruiz",
      "party": "D"
    },
    "members": [
      {
        "seat": 1,
        "seat_label": "",
        "incumbent": {
          "name": "Teresa Ruiz",
          "party": "D"
        },
        "candidates": {
          "rep": "No candidate",
          "dem": "No candidate"
        }
      }
    ],
    "demographics": {
      "population": 111587,
      "rural_pct": 0.0,
      "town_pct": 0.0,
      "suburban_pct": 10.0,
      "urban_pct": 89.9,
      "income_brackets": {
        "lt_50k": 43.2,
        "between_50_100k": 19.3,
        "gt_150k": 11.6,
        "unknown_pct": 25.8
      },
      "college_pct": 11.1,
      "post_grad_pct": 3.2,
      "education_unknown_pct": 46.6,
      "white_pct": 9.6,
      "hispanic_pct": 43.9,
      "black_pct": 30.9,
      "asian_pct": 2.6,
      "other_pct": 12.9
    },
    "elections": [
      {
        "year": 2023,
        "dem_pct": 83.5,
        "rep_pct": 14.5,
        "winner": "D"
      }
    ],
    "view_margins": {
      "leg_2023": 69.0,
      "latest_leg": 69.0,
      "pres_2024": 40.8
    },
    "pres_2024_margin": 40.8,
    "gov_2022_margin": null,
    "top_ticket_totals": {
      "pres_2024": 47081,
      "gov_2022": 0
    },
    "candidates_2026": {
      "rep": "No candidate",
      "dem": "No candidate"
    }
  },
  {
    "state_fips": "34",
    "district_id": "030",
    "district_name": "",
    "incumbent": {
      "name": "Robert W. Singer",
      "party": "R"
    },
    "members": [
      {
        "seat": 1,
        "seat_label": "",
        "incumbent": {
          "name": "Robert W. Singer",
          "party": "R"
        },
        "candidates": {
          "rep": "No candidate",
          "dem": "No candidate"
        }
      }
    ],
    "demographics": {
      "population": 140452,
      "rural_pct": 3.8,
      "town_pct": 0.0,
      "suburban_pct": 72.4,
      "urban_pct": 23.4,
      "income_brackets": {
        "lt_50k": 9.7,
        "between_50_100k": 17.8,
        "gt_150k": 56.0,
        "unknown_pct": 16.5
      },
      "college_pct": 15.9,
      "post_grad_pct": 9.3,
      "education_unknown_pct": 32.9,
      "white_pct": 77.8,
      "hispanic_pct": 6.1,
      "black_pct": 1.5,
      "asian_pct": 2.2,
      "other_pct": 12.5
    },
    "elections": [
      {
        "year": 2023,
        "dem_pct": 19.4,
        "rep_pct": 80.6,
        "winner": "R"
      }
    ],
    "view_margins": {
      "leg_2023": -61.3,
      "latest_leg": -61.3,
      "pres_2024": -46.4
    },
    "pres_2024_margin": -46.4,
    "gov_2022_margin": null,
    "top_ticket_totals": {
      "pres_2024": 96548,
      "gov_2022": 0
    },
    "candidates_2026": {
      "rep": "No candidate",
      "dem": "No candidate"
    }
  },
  {
    "state_fips": "34",
    "district_id": "031",
    "district_name": "",
    "incumbent": {
      "name": "Angela V. McKnight",
      "party": "D"
    },
    "members": [
      {
        "seat": 1,
        "seat_label": "",
        "incumbent": {
          "name": "Angela V. McKnight",
          "party": "D"
        },
        "candidates": {
          "rep": "No candidate",
          "dem": "No candidate"
        }
      }
    ],
    "demographics": {
      "population": 149953,
      "rural_pct": 0.0,
      "town_pct": 0.0,
      "suburban_pct": 46.2,
      "urban_pct": 53.6,
      "income_brackets": {
        "lt_50k": 25.1,
        "between_50_100k": 26.1,
        "gt_150k": 28.2,
        "unknown_pct": 20.6
      },
      "college_pct": 13.5,
      "post_grad_pct": 4.9,
      "education_unknown_pct": 39.9,
      "white_pct": 26.8,
      "hispanic_pct": 30.6,
      "black_pct": 21.9,
      "asian_pct": 7.7,
      "other_pct": 13.0
    },
    "elections": [
      {
        "year": 2023,
        "dem_pct": 75.8,
        "rep_pct": 24.2,
        "winner": "D"
      }
    ],
    "view_margins": {
      "leg_2023": 51.7,
      "latest_leg": 51.7,
      "pres_2024": 27.5
    },
    "pres_2024_margin": 27.5,
    "gov_2022_margin": null,
    "top_ticket_totals": {
      "pres_2024": 76685,
      "gov_2022": 0
    },
    "candidates_2026": {
      "rep": "No candidate",
      "dem": "No candidate"
    }
  },
  {
    "state_fips": "34",
    "district_id": "032",
    "district_name": "",
    "incumbent": {
      "name": "Raj Mukherji",
      "party": "D"
    },
    "members": [
      {
        "seat": 1,
        "seat_label": "",
        "incumbent": {
          "name": "Raj Mukherji",
          "party": "D"
        },
        "candidates": {
          "rep": "No candidate",
          "dem": "No candidate"
        }
      }
    ],
    "demographics": {
      "population": 143105,
      "rural_pct": 0.0,
      "town_pct": 0.0,
      "suburban_pct": 30.5,
      "urban_pct": 69.2,
      "income_brackets": {
        "lt_50k": 13.7,
        "between_50_100k": 16.4,
        "gt_150k": 47.8,
        "unknown_pct": 22.0
      },
      "college_pct": 14.1,
      "post_grad_pct": 6.1,
      "education_unknown_pct": 38.4,
      "white_pct": 46.0,
      "hispanic_pct": 19.8,
      "black_pct": 3.5,
      "asian_pct": 14.5,
      "other_pct": 16.1
    },
    "elections": [
      {
        "year": 2023,
        "dem_pct": 83.1,
        "rep_pct": 16.9,
        "winner": "D"
      }
    ],
    "view_margins": {
      "leg_2023": 66.2,
      "latest_leg": 66.2,
      "pres_2024": 43.2
    },
    "pres_2024_margin": 43.2,
    "gov_2022_margin": null,
    "top_ticket_totals": {
      "pres_2024": 77470,
      "gov_2022": 0
    },
    "candidates_2026": {
      "rep": "No candidate",
      "dem": "No candidate"
    }
  },
  {
    "state_fips": "34",
    "district_id": "033",
    "district_name": "",
    "incumbent": {
      "name": "Brian P. Stack",
      "party": "D"
    },
    "members": [
      {
        "seat": 1,
        "seat_label": "",
        "incumbent": {
          "name": "Brian P. Stack",
          "party": "D"
        },
        "candidates": {
          "rep": "No candidate",
          "dem": "No candidate"
        }
      }
    ],
    "demographics": {
      "population": 128806,
      "rural_pct": 0.0,
      "town_pct": 0.0,
      "suburban_pct": 99.8,
      "urban_pct": 0.1,
      "income_brackets": {
        "lt_50k": 26.7,
        "between_50_100k": 24.3,
        "gt_150k": 28.3,
        "unknown_pct": 20.7
      },
      "college_pct": 14.1,
      "post_grad_pct": 5.4,
      "education_unknown_pct": 42.8,
      "white_pct": 20.5,
      "hispanic_pct": 58.3,
      "black_pct": 1.8,
      "asian_pct": 7.2,
      "other_pct": 12.2
    },
    "elections": [
      {
        "year": 2023,
        "dem_pct": 97.1,
        "rep_pct": 0.0,
        "winner": "D"
      }
    ],
    "view_margins": {
      "leg_2023": 97.1,
      "latest_leg": 97.1,
      "pres_2024": 13.0
    },
    "pres_2024_margin": 13.0,
    "gov_2022_margin": null,
    "top_ticket_totals": {
      "pres_2024": 72757,
      "gov_2022": 0
    },
    "candidates_2026": {
      "rep": "No candidate",
      "dem": "No candidate"
    }
  },
  {
    "state_fips": "34",
    "district_id": "034",
    "district_name": "",
    "incumbent": {
      "name": "Britnee Timberlake",
      "party": "D"
    },
    "members": [
      {
        "seat": 1,
        "seat_label": "",
        "incumbent": {
          "name": "Britnee Timberlake",
          "party": "D"
        },
        "candidates": {
          "rep": "No candidate",
          "dem": "No candidate"
        }
      }
    ],
    "demographics": {
      "population": 162396,
      "rural_pct": 0.0,
      "town_pct": 0.0,
      "suburban_pct": 99.6,
      "urban_pct": 0.2,
      "income_brackets": {
        "lt_50k": 25.6,
        "between_50_100k": 24.4,
        "gt_150k": 32.9,
        "unknown_pct": 17.1
      },
      "college_pct": 15.3,
      "post_grad_pct": 6.6,
      "education_unknown_pct": 34.2,
      "white_pct": 27.3,
      "hispanic_pct": 22.8,
      "black_pct": 34.7,
      "asian_pct": 4.7,
      "other_pct": 10.5
    },
    "elections": [
      {
        "year": 2023,
        "dem_pct": 76.1,
        "rep_pct": 23.9,
        "winner": "D"
      }
    ],
    "view_margins": {
      "leg_2023": 52.1,
      "latest_leg": 52.1,
      "pres_2024": 40.2
    },
    "pres_2024_margin": 40.2,
    "gov_2022_margin": null,
    "top_ticket_totals": {
      "pres_2024": 90467,
      "gov_2022": 0
    },
    "candidates_2026": {
      "rep": "No candidate",
      "dem": "No candidate"
    }
  },
  {
    "state_fips": "34",
    "district_id": "035",
    "district_name": "",
    "incumbent": {
      "name": "Benjie Wimberly",
      "party": "D"
    },
    "members": [
      {
        "seat": 1,
        "seat_label": "",
        "incumbent": {
          "name": "Benjie Wimberly",
          "party": "D"
        },
        "candidates": {
          "rep": "No candidate",
          "dem": "No candidate"
        }
      }
    ],
    "demographics": {
      "population": 137481,
      "rural_pct": 0.0,
      "town_pct": 0.0,
      "suburban_pct": 99.8,
      "urban_pct": 0.0,
      "income_brackets": {
        "lt_50k": 35.6,
        "between_50_100k": 21.7,
        "gt_150k": 20.0,
        "unknown_pct": 22.7
      },
      "college_pct": 12.4,
      "post_grad_pct": 3.9,
      "education_unknown_pct": 43.6,
      "white_pct": 22.3,
      "hispanic_pct": 43.4,
      "black_pct": 16.0,
      "asian_pct": 6.1,
      "other_pct": 12.2
    },
    "elections": [
      {
        "year": 2023,
        "dem_pct": 69.0,
        "rep_pct": 31.0,
        "winner": "D"
      }
    ],
    "view_margins": {
      "leg_2023": 38.0,
      "latest_leg": 38.0,
      "pres_2024": 12.4
    },
    "pres_2024_margin": 12.4,
    "gov_2022_margin": null,
    "top_ticket_totals": {
      "pres_2024": 70419,
      "gov_2022": 0
    },
    "candidates_2026": {
      "rep": "No candidate",
      "dem": "No candidate"
    }
  },
  {
    "state_fips": "34",
    "district_id": "036",
    "district_name": "",
    "incumbent": {
      "name": "Paul Sarlo",
      "party": "D"
    },
    "members": [
      {
        "seat": 1,
        "seat_label": "",
        "incumbent": {
          "name": "Paul Sarlo",
          "party": "D"
        },
        "candidates": {
          "rep": "No candidate",
          "dem": "No candidate"
        }
      }
    ],
    "demographics": {
      "population": 134778,
      "rural_pct": 0.0,
      "town_pct": 0.0,
      "suburban_pct": 99.7,
      "urban_pct": 0.0,
      "income_brackets": {
        "lt_50k": 18.3,
        "between_50_100k": 21.9,
        "gt_150k": 42.3,
        "unknown_pct": 17.5
      },
      "college_pct": 15.5,
      "post_grad_pct": 7.3,
      "education_unknown_pct": 35.9,
      "white_pct": 41.6,
      "hispanic_pct": 33.7,
      "black_pct": 2.3,
      "asian_pct": 10.2,
      "other_pct": 12.1
    },
    "elections": [
      {
        "year": 2023,
        "dem_pct": 61.7,
        "rep_pct": 38.3,
        "winner": "D"
      }
    ],
    "view_margins": {
      "leg_2023": 23.3,
      "latest_leg": 23.3,
      "pres_2024": -4.5
    },
    "pres_2024_margin": -4.5,
    "gov_2022_margin": null,
    "top_ticket_totals": {
      "pres_2024": 81989,
      "gov_2022": 0
    },
    "candidates_2026": {
      "rep": "No candidate",
      "dem": "No candidate"
    }
  },
  {
    "state_fips": "34",
    "district_id": "037",
    "district_name": "",
    "incumbent": {
      "name": "Gordon M. Johnson",
      "party": "D"
    },
    "members": [
      {
        "seat": 1,
        "seat_label": "",
        "incumbent": {
          "name": "Gordon M. Johnson",
          "party": "D"
        },
        "candidates": {
          "rep": "No candidate",
          "dem": "No candidate"
        }
      }
    ],
    "demographics": {
      "population": 154334,
      "rural_pct": 0.0,
      "town_pct": 0.0,
      "suburban_pct": 99.8,
      "urban_pct": 0.0,
      "income_brackets": {
        "lt_50k": 11.3,
        "between_50_100k": 21.3,
        "gt_150k": 51.8,
        "unknown_pct": 15.6
      },
      "college_pct": 16.7,
      "post_grad_pct": 11.6,
      "education_unknown_pct": 33.0,
      "white_pct": 36.8,
      "hispanic_pct": 22.0,
      "black_pct": 11.3,
      "asian_pct": 18.6,
      "other_pct": 11.3
    },
    "elections": [
      {
        "year": 2023,
        "dem_pct": 72.1,
        "rep_pct": 27.9,
        "winner": "D"
      }
    ],
    "view_margins": {
      "leg_2023": 44.3,
      "latest_leg": 44.3,
      "pres_2024": 23.1
    },
    "pres_2024_margin": 23.1,
    "gov_2022_margin": null,
    "top_ticket_totals": {
      "pres_2024": 94132,
      "gov_2022": 0
    },
    "candidates_2026": {
      "rep": "No candidate",
      "dem": "No candidate"
    }
  },
  {
    "state_fips": "34",
    "district_id": "038",
    "district_name": "",
    "incumbent": {
      "name": "Joseph Lagana",
      "party": "D"
    },
    "members": [
      {
        "seat": 1,
        "seat_label": "",
        "incumbent": {
          "name": "Joseph Lagana",
          "party": "D"
        },
        "candidates": {
          "rep": "No candidate",
          "dem": "No candidate"
        }
      }
    ],
    "demographics": {
      "population": 160592,
      "rural_pct": 0.0,
      "town_pct": 0.0,
      "suburban_pct": 99.6,
      "urban_pct": 0.0,
      "income_brackets": {
        "lt_50k": 9.0,
        "between_50_100k": 19.0,
        "gt_150k": 59.2,
        "unknown_pct": 12.8
      },
      "college_pct": 18.5,
      "post_grad_pct": 10.5,
      "education_unknown_pct": 28.9,
      "white_pct": 50.9,
      "hispanic_pct": 22.5,
      "black_pct": 2.1,
      "asian_pct": 13.8,
      "other_pct": 10.6
    },
    "elections": [
      {
        "year": 2023,
        "dem_pct": 57.1,
        "rep_pct": 42.9,
        "winner": "D"
      }
    ],
    "view_margins": {
      "leg_2023": 14.2,
      "latest_leg": 14.2,
      "pres_2024": -0.0
    },
    "pres_2024_margin": -0.0,
    "gov_2022_margin": null,
    "top_ticket_totals": {
      "pres_2024": 108790,
      "gov_2022": 0
    },
    "candidates_2026": {
      "rep": "No candidate",
      "dem": "No candidate"
    }
  },
  {
    "state_fips": "34",
    "district_id": "039",
    "district_name": "",
    "incumbent": {
      "name": "Holly Schepisi",
      "party": "R"
    },
    "members": [
      {
        "seat": 1,
        "seat_label": "",
        "incumbent": {
          "name": "Holly Schepisi",
          "party": "R"
        },
        "candidates": {
          "rep": "No candidate",
          "dem": "No candidate"
        }
      }
    ],
    "demographics": {
      "population": 186289,
      "rural_pct": 0.4,
      "town_pct": 0.0,
      "suburban_pct": 99.1,
      "urban_pct": 0.0,
      "income_brackets": {
        "lt_50k": 4.6,
        "between_50_100k": 12.5,
        "gt_150k": 72.8,
        "unknown_pct": 10.1
      },
      "college_pct": 21.3,
      "post_grad_pct": 14.0,
      "education_unknown_pct": 22.8,
      "white_pct": 68.8,
      "hispanic_pct": 8.5,
      "black_pct": 1.1,
      "asian_pct": 12.1,
      "other_pct": 9.5
    },
    "elections": [
      {
        "year": 2023,
        "dem_pct": 45.1,
        "rep_pct": 54.9,
        "winner": "R"
      }
    ],
    "view_margins": {
      "leg_2023": -9.9,
      "latest_leg": -9.9,
      "pres_2024": -2.3
    },
    "pres_2024_margin": -2.3,
    "gov_2022_margin": null,
    "top_ticket_totals": {
      "pres_2024": 131773,
      "gov_2022": 0
    },
    "candidates_2026": {
      "rep": "No candidate",
      "dem": "No candidate"
    }
  },
  {
    "state_fips": "34",
    "district_id": "040",
    "district_name": "",
    "incumbent": {
      "name": "Kristin Corrado",
      "party": "R"
    },
    "members": [
      {
        "seat": 1,
        "seat_label": "",
        "incumbent": {
          "name": "Kristin Corrado",
          "party": "R"
        },
        "candidates": {
          "rep": "No candidate",
          "dem": "No candidate"
        }
      }
    ],
    "demographics": {
      "population": 187779,
      "rural_pct": 0.1,
      "town_pct": 0.0,
      "suburban_pct": 99.4,
      "urban_pct": 0.0,
      "income_brackets": {
        "lt_50k": 6.2,
        "between_50_100k": 15.5,
        "gt_150k": 67.8,
        "unknown_pct": 10.4
      },
      "college_pct": 20.6,
      "post_grad_pct": 13.4,
      "education_unknown_pct": 23.6,
      "white_pct": 68.9,
      "hispanic_pct": 12.2,
      "black_pct": 1.4,
      "asian_pct": 8.0,
      "other_pct": 9.5
    },
    "elections": [
      {
        "year": 2023,
        "dem_pct": 43.7,
        "rep_pct": 56.3,
        "winner": "R"
      }
    ],
    "view_margins": {
      "leg_2023": -12.5,
      "latest_leg": -12.5,
      "pres_2024": -7.4
    },
    "pres_2024_margin": -7.4,
    "gov_2022_margin": null,
    "top_ticket_totals": {
      "pres_2024": 128512,
      "gov_2022": 0
    },
    "candidates_2026": {
      "rep": "No candidate",
      "dem": "No candidate"
    }
  }
]
